thztools/__init__.py
thztools/ip.py
thztools/jiami.py
thztools-1.0.5.dist-info/METADATA
thztools-1.0.5.dist-info/WHEEL
thztools-1.0.5.dist-info/top_level.txt
thztools-1.0.5.dist-info/RECORD
