Metadata-Version: 2.1
Name: thztools
Version: 1.0.5
Summary: 由天狐宗开发的工具，方便开发时使用
Home-page: https://github.com/tianhuzong/thztools
Author: Sen
Author-email: tianhuzong@qq.com
License: MIT
Classifier: Programming Language :: Python :: 3
Classifier: License :: OSI Approved :: MIT License
Classifier: Operating System :: OS Independent
Requires-Dist: rsa
Requires-Dist: Crypto
Requires-Dist: 2ip
